ibug/__init__.py
ibug/base.py
ibug/classes.py
ibug/parsers/__init__.py
ibug/parsers/_tree32.c
ibug/parsers/_tree32.cp310-win_amd64.pyd
ibug/parsers/_tree64.c
ibug/parsers/_tree64.cp310-win_amd64.pyd
ibug/parsers/parser_cb.py
ibug/parsers/parser_lgb.py
ibug/parsers/parser_ngb.py
ibug/parsers/parser_pgb.py
ibug/parsers/parser_sk.py
ibug/parsers/parser_xgb.py
ibug/parsers/setup.py
ibug/parsers/tree.py
ibug/parsers/util.py
ibug-0.0.11.dist-info/LICENSE
ibug-0.0.11.dist-info/METADATA
ibug-0.0.11.dist-info/WHEEL
ibug-0.0.11.dist-info/top_level.txt
ibug-0.0.11.dist-info/RECORD
