Metadata-Version: 2.1
Name: ibug
Version: 0.0.11
Summary: Instance-Based Uncertainty Estimation for Gradient-Boosted Regression Trees
Home-page: https://github.com/jjbrophy47/ibug
Author: Jonathan Brophy
Author-email: jonathanbrophy47@gmail.com
Classifier: Programming Language :: Python :: 3.9
Classifier: Programming Language :: Python :: 3.10
Classifier: License :: OSI Approved :: Apache Software License
Classifier: Operating System :: OS Independent
Requires-Python: >=3.9
License-File: LICENSE
Requires-Dist: numpy >=1.22
Requires-Dist: uncertainty-toolbox >=0.1.0
Requires-Dist: joblib >=1.1.0
Requires-Dist: scikit-learn >=1.1.1
Requires-Dist: scipy >=1.8.1
Requires-Dist: pandas >=1.4.3
Requires-Dist: Cython >=0.29.23
Requires-Dist: xgboost >=1.6.1
